tekdatamuse/__init__.py
tekdatamuse/api_client.py
tekdatamuse/commands.py
pytekdatamuse-0.1.0.dist-info/LICENSE
pytekdatamuse-0.1.0.dist-info/METADATA
pytekdatamuse-0.1.0.dist-info/WHEEL
pytekdatamuse-0.1.0.dist-info/entry_points.txt
pytekdatamuse-0.1.0.dist-info/top_level.txt
pytekdatamuse-0.1.0.dist-info/RECORD
